lib_dzne_workbook/__init__.py
lib_dzne_workbook-0.4.1.dist-info/LICENSE.txt
lib_dzne_workbook-0.4.1.dist-info/METADATA
lib_dzne_workbook-0.4.1.dist-info/WHEEL
lib_dzne_workbook-0.4.1.dist-info/top_level.txt
lib_dzne_workbook-0.4.1.dist-info/RECORD
