Metadata-Version: 2.1
Name: lib-dzne-workbook
Version: 0.4.1
Summary: Library for handling workbooks.
Author-email: Johannes <johannes-programming@posteo.org>
License: The MIT License (MIT)
Project-URL: Download, https://pypi.org/project/lib-dzne-workbook/#files
Project-URL: Source, https://github.com/johannes-programming/lib_dzne_workbook
Classifier: License :: OSI Approved :: MIT License
Classifier: Programming Language :: Python
Classifier: Programming Language :: Python :: 3
Requires-Python: >=3.11
License-File: LICENSE.txt
Requires-Dist: pandas >=1.4.2
Requires-Dist: openpyxl >=3.0.10
Requires-Dist: lib-dzne-filedata
